README.md
setup.cfg
setup.py
weberTools/__init__.py
weberTools.egg-info/PKG-INFO
weberTools.egg-info/SOURCES.txt
weberTools.egg-info/dependency_links.txt
weberTools.egg-info/not-zip-safe
weberTools.egg-info/top_level.txt
weberTools/FtpTools/CFtpUploadBakYMD.py
weberTools/FtpTools/__init__.py
weberTools/SftpTools/CSFtpDownloadDel.py
weberTools/SftpTools/CSFtpUploadBakYMD.py
weberTools/SftpTools/CSFtpUploadBakup.py
weberTools/SftpTools/__init__.py
weberTools/FtpTools/CFtpUploadBakYMD.py
weberTools/FtpTools/__init__.py
weberTools/SftpTools/CSFtpDownloadDel.py
weberTools/SftpTools/CSFtpUploadBakYMD.py
weberTools/SftpTools/CSFtpUploadBakup.py
weberTools/SftpTools/__init__.py