Metadata-Version: 1.1
Name: weberTools
Version: 0.0.24
Summary: Public tools library wrote by Weber Juche.
Home-page: https://github.com/Weber-JC/PythonEggs/tree/master/weberTools
Author: Weber Juche
Author-email: weber.juche@gmail.com
License: MIT
Keywords: public weberTools weber
Platform: UNKNOWN
Classifier: License :: OSI Approved :: MIT License
Classifier: Programming Language :: Python
Classifier: Intended Audience :: Developers
Classifier: Operating System :: OS Independent
